wf_data_monitor/__init__.py
wf_data_monitor/__main__.py
wf_data_monitor/const.py
wf_data_monitor/honeycomb_db/handle.py
wf_data_monitor/honeycomb_db/queries.py
wf_data_monitor/honeycomb_service/__init__.py
wf_data_monitor/honeycomb_service/client.py
wf_data_monitor/log.py
wf_data_monitor/notifications/__init__.py
wf_data_monitor/notifications/notifier.py
wf_data_monitor/scheduler.py
wf_data_monitor/tasks/__init__.py
wf_data_monitor/tasks/environments/__init__.py
wf_data_monitor/tasks/environments/uwb.py
wf_data_monitor/tasks/environments/video.py
wf_data_monitor/video_service/__init__.py
wf_data_monitor/video_service/client.py
wf_data_monitor-1.0.2.dist-info/LICENSE
wf_data_monitor-1.0.2.dist-info/METADATA
wf_data_monitor-1.0.2.dist-info/WHEEL
wf_data_monitor-1.0.2.dist-info/RECORD
